mixed_methods/__init__.py
mixed_methods/core.py
mixed_methods/py.typed
mixed_methods-1.1.0.dist-info/LICENSE
mixed_methods-1.1.0.dist-info/METADATA
mixed_methods-1.1.0.dist-info/WHEEL
mixed_methods-1.1.0.dist-info/RECORD
