Metadata-Version: 2.1
Name: mixed-methods
Version: 1.1.0
Summary: Mixed methods.
Home-page: https://github.com/nekitdev/mixed-methods
License: MIT
Keywords: python,mixed,method
Author: nekitdev
Requires-Python: >=3.8
Classifier: Development Status :: 5 - Production/Stable
Classifier: Intended Audience :: Developers
Classifier: License :: OSI Approved :: MIT License
Classifier: Operating System :: OS Independent
Classifier: Programming Language :: Python :: 3
Classifier: Programming Language :: Python :: 3.8
Classifier: Programming Language :: Python :: 3.9
Classifier: Programming Language :: Python :: 3.10
Classifier: Programming Language :: Python :: 3.11
Classifier: Programming Language :: Python :: 3.12
Classifier: Topic :: Utilities
Classifier: Typing :: Typed
Requires-Dist: attrs (>=23.2.0,<24.0.0)
Requires-Dist: typing-extensions (>=4.9.0,<5.0.0)
Project-URL: Chat, https://nekit.dev/chat
Project-URL: Documentation, https://nekitdev.github.io/mixed-methods
Project-URL: Funding, https://nekit.dev/funding
Project-URL: Issues, https://github.com/nekitdev/mixed-methods/issues
Project-URL: Repository, https://github.com/nekitdev/mixed-methods
